loggers/__init__.py
loggers/loggers.py
log_decorators-1.0.1.dist-info/METADATA
log_decorators-1.0.1.dist-info/WHEEL
log_decorators-1.0.1.dist-info/top_level.txt
log_decorators-1.0.1.dist-info/RECORD
