Metadata-Version: 2.1
Name: log-decorators
Version: 1.0.1
Summary: A Python library for decorators for functions return values logging in the console or file.
Author: Daniel Stefanov
